recognizers_choice/__init__.py
recognizers_choice/choice/__init__.py
recognizers_choice/choice/constants.py
recognizers_choice/choice/extractors.py
recognizers_choice/choice/models.py
recognizers_choice/choice/parsers.py
recognizers_choice/choice/recognizers_choice.py
recognizers_choice/choice/english/__init__.py
recognizers_choice/choice/english/boolean.py
recognizers_choice/resources/__init__.py
recognizers_choice/resources/english_choice.py
recognizers_text_choice-1.0.2a2.dist-info/METADATA
recognizers_text_choice-1.0.2a2.dist-info/WHEEL
recognizers_text_choice-1.0.2a2.dist-info/top_level.txt
recognizers_text_choice-1.0.2a2.dist-info/RECORD
